{
  "_fv": 69,
  "_type": "item",
  "definition": {
    "renderType": 0,
    "texture": "nautical_crossbow",
    "customModelName": "Ranged item",
    "customProperties": {},
    "states": [],
    "name": "Glory Gold Ghost",
    "rarity": "RARE",
    "creativeTabs": [
      {
        "value": "COMBAT"
      }
    ],
    "stackSize": 1,
    "enchantability": 0,
    "useDuration": 99999,
    "toolType": 1.0,
    "damageCount": 0,
    "recipeRemainder": {
      "value": ""
    },
    "destroyAnyBlock": false,
    "immuneToFire": false,
    "stayInGridWhenCrafting": false,
    "damageOnCrafting": false,
    "enableMeleeDamage": false,
    "damageVsEntity": 0.0,
    "specialInformation": {
      "fixedValue": []
    },
    "glowCondition": {
      "fixedValue": false
    },
    "guiBoundTo": "<NONE>",
    "inventorySize": 9,
    "inventoryStackSize": 64,
    "enableRanged": true,
    "shootConstantly": false,
    "rangedItemChargesPower": false,
    "projectile": {
      "value": "Arrow"
    },
    "projectileDisableAmmoCheck": true,
    "onRangedItemUsed": {
      "name": "GloryGoldGhostEffect"
    },
    "isFood": false,
    "nutritionalValue": 4,
    "saturation": 0.3,
    "eatResultItem": {
      "value": ""
    },
    "isMeat": false,
    "isAlwaysEdible": false,
    "animation": "crossbow"
  }
}